hallucinot/__init__.py
hallucinot/cli.py
hallucinot/processor.py
hallucinot-0.1.0.dist-info/LICENSE
hallucinot-0.1.0.dist-info/METADATA
hallucinot-0.1.0.dist-info/WHEEL
hallucinot-0.1.0.dist-info/entry_points.txt
hallucinot-0.1.0.dist-info/top_level.txt
hallucinot-0.1.0.dist-info/RECORD
