Metadata-Version: 2.2
Name: hallucinot
Version: 0.1.0
Summary: Document-Grounded Verification for Large Language Models
Author-email: Kris Naleszkiewicz <kris.nale@gmail.com>
License: MIT
Project-URL: Homepage, https://github.com/Kris-Nale314/hallucinot
Project-URL: Bug Tracker, https://github.com/Kris-Nale314/hallucinot/issues
Project-URL: Documentation, https://github.com/Kris-Nale314/hallucinot/tree/main/docs
Project-URL: Source Code, https://github.com/Kris-Nale314/hallucinot
Classifier: Development Status :: 3 - Alpha
Classifier: Intended Audience :: Developers
Classifier: Intended Audience :: Science/Research
Classifier: License :: OSI Approved :: MIT License
Classifier: Programming Language :: Python :: 3
Classifier: Programming Language :: Python :: 3.8
Classifier: Programming Language :: Python :: 3.9
Classifier: Programming Language :: Python :: 3.10
Classifier: Topic :: Scientific/Engineering :: Artificial Intelligence
Classifier: Topic :: Text Processing :: Linguistic
Requires-Python: >=3.8
License-File: LICENSE
Requires-Dist: numpy>=1.20.0
Requires-Dist: tqdm>=4.62.0
Requires-Dist: requests>=2.25.0
Requires-Dist: pydantic>=1.9.0
Provides-Extra: dev
Requires-Dist: pytest>=7.0.0; extra == "dev"
Requires-Dist: pytest-cov>=3.0.0; extra == "dev"
Requires-Dist: black>=22.3.0; extra == "dev"
Requires-Dist: isort>=5.10.0; extra == "dev"
Requires-Dist: flake8>=4.0.0; extra == "dev"
Requires-Dist: mypy>=0.950; extra == "dev"
Provides-Extra: nlp
Requires-Dist: spacy>=3.0.0; extra == "nlp"
Provides-Extra: bytemesumai
Requires-Dist: bytemesumai>=0.1.0; extra == "bytemesumai"
Provides-Extra: visualizations
Requires-Dist: matplotlib>=3.5.0; extra == "visualizations"
Requires-Dist: seaborn>=0.11.0; extra == "visualizations"
Provides-Extra: all
Requires-Dist: spacy>=3.0.0; extra == "all"
Requires-Dist: bytemesumai>=0.1.0; extra == "all"
Requires-Dist: matplotlib>=3.5.0; extra == "all"
Requires-Dist: seaborn>=0.11.0; extra == "all"
